gkeepapi/__init__.py
gkeepapi/exception.py
gkeepapi/node.py
gkeepapi-0.17.0.dist-info/licenses/LICENSE.txt
gkeepapi-0.17.0.dist-info/WHEEL
gkeepapi-0.17.0.dist-info/METADATA
gkeepapi-0.17.0.dist-info/RECORD
