Metadata-Version: 2.4
Name: gkeepapi
Version: 0.17.0
Summary: An unofficial Google Keep API client
Author-email: Kai <z@kwi.li>
Requires-Python: >=3.10
Classifier: Programming Language :: Python :: 3
Classifier: License :: OSI Approved :: MIT License
Classifier: Development Status :: 4 - Beta
Classifier: Operating System :: OS Independent
Classifier: Intended Audience :: Developers
Classifier: Topic :: Internet :: WWW/HTTP
Classifier: Topic :: Software Development :: Libraries :: Python Modules
License-File: LICENSE.txt
Requires-Dist: gpsoauth >= 1.1.0
Requires-Dist: future >= 0.16.0
Requires-Dist: build>=1.3.0
Requires-Dist: ruff>=0.1.14 ; extra == "dev"
Requires-Dist: coverage>=7.2.5 ; extra == "dev"
Requires-Dist: Sphinx>=7.2.6 ; extra == "dev"
Project-URL: Bug Tracker, https://github.com/kiwiz/gkeepapi/issues
Project-URL: Homepage, https://github.com/kiwiz/gkeepapi
Provides-Extra: dev
